process_HDST/__init__.py
process_HDST/afterPreprocess.py
process_HDST/cli.py
process_hdst-0.0.13.dist-info/METADATA
process_hdst-0.0.13.dist-info/WHEEL
process_hdst-0.0.13.dist-info/entry_points.txt
process_hdst-0.0.13.dist-info/top_level.txt
process_hdst-0.0.13.dist-info/RECORD
